sardine/__init__.py
sardine/_sardine.cpython-312-x86_64-linux-gnu.so
sardine/cache.py
sardine/libsardine.so
sardine/managed.py
sardine/sync.py
sardine/utils.py
sardine/buffer/__init__.py
sardine/host/__init__.py
sardine/host/file.py
sardine/host/shm.py
sardine/milk/__init__.py
sardine/url/__init__.py
sardine/url/url.py
sardine/url/utils.py
sardine_cli/__init__.py
sardine_cli/cli.py
cosmic_sardine-0.1.1.dist-info/METADATA
cosmic_sardine-0.1.1.dist-info/WHEEL
cosmic_sardine-0.1.1.dist-info/entry_points.txt
cosmic_sardine-0.1.1.dist-info/RECORD
cosmic_sardine-0.1.1.dist-info/licenses/LICENSE
