Metadata-Version: 2.1
Name: cosmic-sardine
Version: 0.1.1
Summary: Shared memory for Sardine
Keywords: shm,pybind11
Author-Email: Julien Bernard <julientom.bernard@anu.edu.au>
License: MIT License
Classifier: Development Status :: 3 - Alpha
Classifier: License :: OSI Approved :: MIT License
Classifier: Programming Language :: Python :: 3
Classifier: Programming Language :: Python :: 3.10
Classifier: Programming Language :: Python :: 3.11
Classifier: Programming Language :: Python :: 3.12
Classifier: Programming Language :: Python :: 3.13
Classifier: Operating System :: POSIX :: Linux
Requires-Python: >=3.10
Requires-Dist: numpy>=2.2.1
Requires-Dist: cosmic-sardine-milk; extra == "milk"
Requires-Dist: cosmic-sardine-cuda; extra == "cuda"
Provides-Extra: milk
Provides-Extra: cuda
